tinbox_client/version.py
tinbox_client/__init__.py
tinbox_client/client.py
tinbox_client/auth.py
tinbox_client/settings.py
tinbox_client-1.0.1.dist-info/RECORD
tinbox_client-1.0.1.dist-info/DESCRIPTION.rst
tinbox_client-1.0.1.dist-info/metadata.json
tinbox_client-1.0.1.dist-info/WHEEL
tinbox_client-1.0.1.dist-info/top_level.txt
tinbox_client-1.0.1.dist-info/METADATA
