Metadata-Version: 2.0
Name: tinbox-client
Version: 1.0.1
Summary: Tinbox client library
Home-page: https://github.com/5monkeys/tinbox-client
Author: Joar Wandborg
Author-email: joar@5monkeys.se
License: MIT
Platform: UNKNOWN
Requires-Dist: requests-oauthlib (==0.4.2)
